README.txt
setup.py
bin/prex-image.py
bin/prex-server.py
src/prex/__init__.py
src/prex/client.py
src/prex/message_pb2.py
src/prex/server.py
src/prex.egg-info/PKG-INFO
src/prex.egg-info/SOURCES.txt
src/prex.egg-info/dependency_links.txt
src/prex.egg-info/requires.txt
src/prex.egg-info/top_level.txt