Metadata-Version: 1.1
Name: prex
Version: 0.2.4
Summary: Execute Python scripts on a remote sandbox
Home-page: http://github.com/BaroboRobotics/prex
Author: David Ko
Author-email: david@barobo.com
License: UNKNOWN
Platform: UNKNOWN
Classifier: Development Status :: 3 - Alpha
Classifier: Operating System :: OS Independent
Classifier: Programming Language :: Python :: 3.5
